package_repo/__init__.py
package_repo/__version__.py
package_repo/_api.py
package_repo/example_etl.py
package_repo/example_sql_connection.py
package_repo/examples.py
package_repo/logger.py
package_repo-0.0.3.dist-info/METADATA
package_repo-0.0.3.dist-info/WHEEL
package_repo-0.0.3.dist-info/RECORD
