Metadata-Version: 2.1
Name: package_repo
Version: 0.0.3
Summary: A short description of the package.
Author: Klim Mikhailov
Author-email: k.mikhailov@rotterdam.nl
Requires-Python: >=3.11,<4.0
Classifier: Programming Language :: Python :: 3
Classifier: Programming Language :: Python :: 3.11
Classifier: Programming Language :: Python :: 3.12
Requires-Dist: ipykernel (>=6.21.0,<7.0.0)
Requires-Dist: poetry-plugin-export (>=1.6.0,<2.0.0)
Requires-Dist: python-dotenv (>=0.21.1,<0.22.0)
